bactovision/__init__.py
bactovision/canvas.js
bactovision/canvas_widget.py
bactovision/grid_config.py
bactovision/image_processing.py
bactovision/widget.py
bactovision-0.1.2.dist-info/licenses/LICENSE.txt
bactovision-0.1.2.dist-info/METADATA
bactovision-0.1.2.dist-info/WHEEL
bactovision-0.1.2.dist-info/top_level.txt
bactovision-0.1.2.dist-info/RECORD
