Metadata-Version: 2.4
Name: bactovision
Version: 0.1.2
Summary: A package for bacterial image processing
Home-page: https://github.com/StarostinV/bactovision
Author: Vladimir Starostin
Author-email: vladimir.starostin@uni-tuebingen.de
Requires-Python: >=3.8
License-File: LICENSE.txt
Requires-Dist: numpy<2.0.0,>=1.20.0
Requires-Dist: scipy<1.15.0,>=1.8.0
Requires-Dist: scikit-image>=0.18.0
Requires-Dist: Pillow>=9.0.0
Requires-Dist: opencv-python>=4.5.0
Requires-Dist: anywidget>=0.1.0
Requires-Dist: traitlets>=5.0.0
Requires-Dist: matplotlib>=3.5.0
Requires-Dist: jupyterlab>=3.0.0
Dynamic: author
Dynamic: author-email
Dynamic: description
Dynamic: description-content-type
Dynamic: home-page
Dynamic: license-file
Dynamic: requires-dist
Dynamic: requires-python
Dynamic: summary
